COPYING
MANIFEST.in
NEWS.md
README.md
pyproject.toml
python_via.egg-info/PKG-INFO
python_via.egg-info/SOURCES.txt
python_via.egg-info/dependency_links.txt
python_via.egg-info/requires.txt
python_via.egg-info/top_level.txt
via/__init__.py
via/coco.py
via/lisa.py
via/vfs.py
via/via3.py