Metadata-Version: 2.1
Name: python-via
Version: 0.0.4
Summary: Tools to handle VIA projects
License: 
Project-URL: homepage, https://www.robots.ox.ac.uk/~vgg/software/via/
Project-URL: news, https://gitlab.com/vgg/python-via/-/blob/main/NEWS.md
Project-URL: repository, https://gitlab.com/vgg/python-via
Project-URL: tracker, https://gitlab.com/vgg/python-via/-/issues
Classifier: Development Status :: 1 - Planning
Classifier: Intended Audience :: Science/Research
Classifier: License :: OSI Approved :: Apache Software License
Classifier: Topic :: Scientific/Engineering :: Artificial Intelligence
Requires-Python: >=3.9
License-File: COPYING
Requires-Dist: pycocotools
Requires-Dist: requests
